webint_auth/__init__.py
webint_auth/templates/__init__.py
webint_auth/templates/authorizations.html
webint_auth/templates/client.html
webint_auth/templates/clients.html
webint_auth/templates/consent.html
webint_auth/templates/root.html
webint_auth/templates/unauthorized.html
webint_auth-0.0.9.dist-info/METADATA
webint_auth-0.0.9.dist-info/entry_points.txt
webint_auth-0.0.9.dist-info/WHEEL
webint_auth-0.0.9.dist-info/RECORD
